{
  "animateLoading": true,
  "borderRadius": "{{appsmith.theme.borderRadius.appBorderRadius}}",
  "bottomRow": 101,
  "boxShadow": "none",
  "buttonColor": "#3b82f6",
  "buttonVariant": "PRIMARY",
  "disabledWhenInvalid": false,
  "dynamicBindingPathList": [
    {
      "key": "borderRadius"
    }
  ],
  "dynamicPropertyPathList": [],
  "dynamicTriggerPathList": [
    {
      "key": "onClick"
    }
  ],
  "isDefaultClickDisabled": true,
  "isDisabled": false,
  "isLoading": false,
  "isVisible": true,
  "key": "wiqtz3ou8c",
  "leftColumn": 24,
  "minWidth": 120,
  "mobileBottomRow": 109,
  "mobileLeftColumn": 22,
  "mobileRightColumn": 38,
  "mobileTopRow": 105,
  "needsErrorInfo": false,
  "onClick": "{{decisao_rapida.processarDecisao();}}",
  "originalBottomRow": 100,
  "originalTopRow": 95,
  "parentColumnSpace": 11.16015625,
  "parentId": "xkib8f5ov2",
  "parentRowSpace": 10,
  "placement": "CENTER",
  "recaptchaType": "V3",
  "renderMode": "CANVAS",
  "resetFormOnClick": false,
  "responsiveBehavior": "hug",
  "rightColumn": 40,
  "text": "ENVIAR",
  "topRow": 96,
  "type": "BUTTON_WIDGET",
  "version": 1,
  "widgetId": "jz3gm6pgdb",
  "widgetName": "Button1"
}