{
  "animateLoading": true,
  "borderRadius": "{{appsmith.theme.borderRadius.appBorderRadius}}",
  "bottomRow": 16,
  "boxShadow": "none",
  "buttonColor": "green",
  "buttonVariant": "TERTIARY",
  "dynamicBindingPathList": [
    {
      "key": "borderRadius"
    }
  ],
  "dynamicPropertyPathList": [],
  "dynamicTriggerPathList": [
    {
      "key": "onClick"
    }
  ],
  "iconName": "refresh",
  "isDisabled": false,
  "isLoading": false,
  "isVisible": true,
  "key": "sspdpg2m04",
  "leftColumn": 61,
  "minWidth": 50,
  "mobileBottomRow": 8,
  "mobileLeftColumn": 0,
  "mobileRightColumn": 4,
  "mobileTopRow": 4,
  "needsErrorInfo": false,
  "onClick": "{{solicitacoes_frota_list.run()}}",
  "parentColumnSpace": 16.7734375,
  "parentId": "5w67zcvffh",
  "parentRowSpace": 10,
  "renderMode": "CANVAS",
  "responsiveBehavior": "hug",
  "rightColumn": 63,
  "topRow": 12,
  "type": "ICON_BUTTON_WIDGET",
  "version": 1,
  "widgetId": "8evf7oxu2x",
  "widgetName": "IconButton4"
}