{
  "animateLoading": true,
  "borderRadius": "{{appsmith.theme.borderRadius.appBorderRadius}}",
  "bottomRow": 20,
  "boxShadow": "none",
  "defaultImage": "",
  "dynamicBindingPathList": [
    {
      "key": "image"
    },
    {
      "key": "borderRadius"
    }
  ],
  "dynamicTriggerPathList": [],
  "enableDownload": false,
  "enableRotation": false,
  "flexVerticalAlignment": "start",
  "image": "{{ currentItem }}\n",
  "imageShape": "RECTANGLE",
  "isLoading": false,
  "isVisible": true,
  "key": "u4ywztuw5d",
  "leftColumn": 0,
  "maxZoomLevel": 1,
  "mobileBottomRow": 8,
  "mobileLeftColumn": 0,
  "mobileRightColumn": 16,
  "mobileTopRow": 0,
  "needsErrorInfo": false,
  "objectFit": "cover",
  "parentId": "3gxwhh03mu",
  "renderMode": "CANVAS",
  "rightColumn": 61,
  "topRow": 0,
  "type": "IMAGE_WIDGET",
  "version": 1,
  "widgetId": "ab0jnvg99r",
  "widgetName": "Imagem_checklist"
}