{
  "gitSyncId": "684accaaccd99e1ff73d47d3_909ee63f-877e-4c66-b358-da8b25b424e5",
  "id": "home_Query2",
  "pluginId": "postgres-plugin",
  "pluginType": "DB",
  "unpublishedAction": {
    "actionConfiguration": {
      "body": "SELECT \n    matricula,\n    LENGTH(matricula),\n    '\"' || matricula || '\"' AS debug\nFROM compras_so.permissoes_matricula\nWHERE matricula !~ '^[0-9]+$';\n",
      "encodeParamsToggle": true,
      "paginationType": "NONE",
      "pluginSpecifiedTemplates": [
        {
          "value": true
        }
      ],
      "timeoutInMillisecond": 10000
    },
    "confirmBeforeExecute": false,
    "datasource": {
      "id": "CANDIDATOS",
      "isAutoGenerated": false,
      "name": "CANDIDATOS",
      "pluginId": "postgres-plugin"
    },
    "dynamicBindingPathList": [],
    "name": "Query2",
    "pageId": "home",
    "runBehaviour": "MANUAL",
    "userSetOnLoad": false
  }
}