{
  "gitSyncId": "684accaaccd99e1ff73d47d3_8579ab8b-e778-4967-8fd0-54df254261cd",
  "id": "Finaceiro_status_list",
  "pluginId": "postgres-plugin",
  "pluginType": "DB",
  "unpublishedAction": {
    "actionConfiguration": {
      "body": "SELECT \n status\nFROM compras_so.\"manutencao_frotas\"\nWHERE status IS NOT NULL\n  AND TRIM(status) <> '';\n",
      "encodeParamsToggle": true,
      "paginationType": "NONE",
      "pluginSpecifiedTemplates": [
        {
          "value": true
        }
      ],
      "timeoutInMillisecond": 10000
    },
    "confirmBeforeExecute": false,
    "datasource": {
      "id": "CANDIDATOS",
      "isAutoGenerated": false,
      "name": "CANDIDATOS",
      "pluginId": "postgres-plugin"
    },
    "dynamicBindingPathList": [],
    "name": "status_list",
    "pageId": "Finaceiro",
    "runBehaviour": "AUTOMATIC",
    "userSetOnLoad": false
  }
}